msgraphhelper/__init__.py
msgraphhelper/odata.py
msgraphhelper/session.py
msgraphhelper/subscriptions.py
msgraphhelper/url.py
msgraphhelper-0.3.0.dist-info/LICENSE
msgraphhelper-0.3.0.dist-info/METADATA
msgraphhelper-0.3.0.dist-info/WHEEL
msgraphhelper-0.3.0.dist-info/top_level.txt
msgraphhelper-0.3.0.dist-info/RECORD
