Metadata-Version: 2.1
Name: msgraphhelper
Version: 0.3.0
Summary: Handle MS Graph Change Notifications in a Pythonic manner in Azure Functions
Author-email: Giles Antonio Radford <moof@metamoof.net>
Project-URL: Homepage, https://github.com/metamoof/msgraphhelper
Project-URL: Issues, https://github.com/metamoof/msgraphhelper/issues
Keywords: azure-functions,ms-graph,graph,suscription,Webhooks
Classifier: License :: OSI Approved :: MIT License
Classifier: Programming Language :: Python
Classifier: Programming Language :: Python :: 3
Classifier: Development Status :: 3 - Alpha
Classifier: Intended Audience :: Developers
Classifier: Topic :: Software Development :: Libraries :: Python Modules
Classifier: Typing :: Typed
Requires-Python: >=3.9
License-File: LICENSE
Requires-Dist: azure-functions
Requires-Dist: azure-identity
Requires-Dist: azure-data-tables
Requires-Dist: azure-functions-durable
Provides-Extra: dev
Requires-Dist: pytest ; extra == 'dev'
Requires-Dist: black ; extra == 'dev'
Requires-Dist: requests-mock ; extra == 'dev'
